{
   "data" : {
      "result" : [
         {
            "metric" : {
               "__name__" : "request_time_train",
               "instance" : "app_one:8000",
               "job" : "app_one"
            },
            "values" : [
               [
                  1695307054.366,
                  "0.2912175100973161"
               ],
               [
                  1695307059.366,
                  "0.36894227196838225"
               ],
               [
                  1695307064.366,
                  "0.022246105003857375"
               ],
               [
                  1695307069.366,
                  "0.12000495034328285"
               ],
               [
                  1695307074.366,
                  "0.1460237207511117"
               ],
               [
                  1695307079.368,
                  "0.3727495545344197"
               ],
               [
                  1695307084.366,
                  "0.13073319135230088"
               ],
               [
                  1695307089.366,
                  "0.06942571105374551"
               ],
               [
                  1695307094.366,
                  "0.31034482549561837"
               ],
               [
                  1695307099.37,
                  "0.11025408783284485"
               ],
               [
                  1695307104.37,
                  "0.2066521174182835"
               ],
               [
                  1695307109.37,
                  "0.08639107104429344"
               ],
               [
                  1695307114.369,
                  "0.03589037950695151"
               ],
               [
                  1695307119.369,
                  "0.07337765381545236"
               ],
               [
                  1695307124.369,
                  "0.5892792346968846"
               ],
               [
                  1695307129.371,
                  "0.19413755065249727"
               ],
               [
                  1695307134.37,
                  "0.3983551644614697"
               ],
               [
                  1695307139.37,
                  "0.1526488554509171"
               ],
               [
                  1695307144.37,
                  "0.3374452203638191"
               ],
               [
                  1695307149.371,
                  "0.12047132853575271"
               ],
               [
                  1695307154.37,
                  "0.07970656773250906"
               ],
               [
                  1695307159.366,
                  "0.449675243849435"
               ],
               [
                  1695307164.366,
                  "0.25885962195798806"
               ],
               [
                  1695307169.366,
                  "0.5507296900574074"
               ],
               [
                  1695307174.366,
                  "0.5722316316404937"
               ],
               [
                  1695307179.366,
                  "0.34263851752796315"
               ],
               [
                  1695307184.366,
                  "0.2436943100091542"
               ],
               [
                  1695307189.372,
                  "0.5589173791945206"
               ],
               [
                  1695307194.372,
                  "0.0538401768944321"
               ],
               [
                  1695307199.372,
                  "0.4152425408001771"
               ],
               [
                  1695307204.372,
                  "0.31574228362371803"
               ],
               [
                  1695307209.371,
                  "0.37882676381659297"
               ],
               [
                  1695307214.371,
                  "0.5878691119462892"
               ],
               [
                  1695307219.373,
                  "0.06315888078816634"
               ],
               [
                  1695307224.373,
                  "0.0926950189055854"
               ],
               [
                  1695307229.373,
                  "0.4018121251124547"
               ],
               [
                  1695307234.373,
                  "0.10762863877415008"
               ],
               [
                  1695307239.373,
                  "0.1560433193297044"
               ],
               [
                  1695307244.373,
                  "0.5254019126266438"
               ],
               [
                  1695307249.374,
                  "0.40382558255261636"
               ],
               [
                  1695307254.374,
                  "0.18223678578994107"
               ],
               [
                  1695307259.375,
                  "0.3298431965573553"
               ],
               [
                  1695307264.374,
                  "0.2980680733242713"
               ],
               [
                  1695307269.374,
                  "0.10764048567684847"
               ],
               [
                  1695307274.375,
                  "0.5686312197531178"
               ],
               [
                  1695307279.375,
                  "0.3932533677225817"
               ],
               [
                  1695307284.375,
                  "0.3237632647055987"
               ],
               [
                  1695307289.375,
                  "0.09144466853703848"
               ],
               [
                  1695307294.374,
                  "0.43459722035415693"
               ],
               [
                  1695307299.375,
                  "0.33657973471198366"
               ],
               [
                  1695307304.375,
                  "0.10692480781343883"
               ],
               [
                  1695307309.376,
                  "0.34764650285801757"
               ],
               [
                  1695307314.375,
                  "0.5964823491546464"
               ],
               [
                  1695307319.376,
                  "0.03466157834773209"
               ],
               [
                  1695307324.376,
                  "0.592916788035336"
               ],
               [
                  1695307329.375,
                  "0.019320663556706807"
               ],
               [
                  1695307334.376,
                  "0.06646632032665234"
               ],
               [
                  1695307339.376,
                  "0.2928257046731594"
               ],
               [
                  1695307344.376,
                  "0.5379457386698736"
               ],
               [
                  1695307349.375,
                  "0.16913280076080162"
               ],
               [
                  1695307354.375,
                  "0.5062565625391282"
               ],
               [
                  1695307359.376,
                  "0.4749200901949441"
               ],
               [
                  1695307364.376,
                  "0.1959446864144081"
               ],
               [
                  1695307369.376,
                  "0.4985557485190695"
               ],
               [
                  1695307374.376,
                  "0.1352145120145648"
               ],
               [
                  1695307379.376,
                  "0.10108085158431013"
               ],
               [
                  1695307384.376,
                  "0.19119216946461715"
               ],
               [
                  1695307389.376,
                  "0.36518220728289286"
               ],
               [
                  1695307394.376,
                  "0.11276859725721744"
               ],
               [
                  1695307399.376,
                  "0.08525159340209831"
               ],
               [
                  1695307404.376,
                  "0.44985499611175284"
               ],
               [
                  1695307409.376,
                  "0.1415142459701294"
               ],
               [
                  1695307414.376,
                  "0.011492761503440918"
               ],
               [
                  1695307419.376,
                  "0.4167347729378472"
               ],
               [
                  1695307424.376,
                  "0.25865562186313795"
               ],
               [
                  1695307429.377,
                  "0.34034565985740295"
               ],
               [
                  1695307434.376,
                  "0.07854965664582514"
               ],
               [
                  1695307439.375,
                  "0.4886355058967927"
               ],
               [
                  1695307444.376,
                  "0.2662536754040685"
               ],
               [
                  1695307449.377,
                  "0.2016819617596246"
               ],
               [
                  1695307454.377,
                  "0.2696457495906114"
               ],
               [
                  1695307459.376,
                  "0.3429930302380785"
               ],
               [
                  1695307464.377,
                  "0.5308029351404469"
               ],
               [
                  1695307469.376,
                  "0.45206340031444947"
               ],
               [
                  1695307474.377,
                  "0.2714715758590376"
               ],
               [
                  1695307479.377,
                  "0.43314382143347496"
               ],
               [
                  1695307484.376,
                  "0.32368321249897936"
               ],
               [
                  1695307489.377,
                  "0.40663887900931106"
               ],
               [
                  1695307494.377,
                  "0.46025322685976944"
               ],
               [
                  1695307499.377,
                  "0.19756012412584423"
               ],
               [
                  1695307504.377,
                  "0.41499635301979"
               ],
               [
                  1695307509.377,
                  "0.22771678422098884"
               ],
               [
                  1695307514.377,
                  "0.07415237958833343"
               ],
               [
                  1695307519.377,
                  "0.4254566205783161"
               ],
               [
                  1695307524.376,
                  "0.5427500284065819"
               ],
               [
                  1695307529.377,
                  "0.5726821918634555"
               ],
               [
                  1695307534.377,
                  "0.17572653345621025"
               ],
               [
                  1695307539.377,
                  "0.4397072834552266"
               ],
               [
                  1695307544.378,
                  "0.5485967909746493"
               ],
               [
                  1695307549.377,
                  "0.16168543283108805"
               ],
               [
                  1695307554.377,
                  "0.2001705403344951"
               ],
               [
                  1695307559.377,
                  "0.3398102610828512"
               ],
               [
                  1695307564.377,
                  "0.3153784805646108"
               ],
               [
                  1695307569.377,
                  "0.31576104729028454"
               ],
               [
                  1695307574.377,
                  "0.21114791743052408"
               ],
               [
                  1695307579.377,
                  "0.3573960468973194"
               ],
               [
                  1695307584.377,
                  "0.5916191852347504"
               ],
               [
                  1695307589.377,
                  "0.4801729120852781"
               ],
               [
                  1695307594.377,
                  "0.3722813980010391"
               ],
               [
                  1695307599.376,
                  "0.46698410496189324"
               ],
               [
                  1695307604.377,
                  "0.19307675774750277"
               ],
               [
                  1695307609.372,
                  "0.30973972420521956"
               ],
               [
                  1695307614.372,
                  "0.4730242751394532"
               ],
               [
                  1695307619.372,
                  "0.038879614372990035"
               ],
               [
                  1695307624.372,
                  "0.05154309414580327"
               ],
               [
                  1695307629.372,
                  "0.46249082204408143"
               ],
               [
                  1695307634.371,
                  "0.2642836126208896"
               ],
               [
                  1695307639.377,
                  "0.0010709873180048124"
               ],
               [
                  1695307644.377,
                  "0.527595787927743"
               ],
               [
                  1695307649.377,
                  "0.0020893266840099622"
               ],
               [
                  1695307654.377,
                  "0.497339536006828"
               ],
               [
                  1695307659.377,
                  "0.5131295100083421"
               ],
               [
                  1695307664.377,
                  "0.008001412082008219"
               ],
               [
                  1695307669.378,
                  "0.09266970046210665"
               ],
               [
                  1695307674.378,
                  "0.05291704926879692"
               ],
               [
                  1695307679.378,
                  "0.019882924225172127"
               ],
               [
                  1695307684.378,
                  "0.1827541376361118"
               ],
               [
                  1695307689.379,
                  "0.07899847668144677"
               ],
               [
                  1695307694.379,
                  "0.3543020877717723"
               ],
               [
                  1695307699.37,
                  "0.4526275390711183"
               ],
               [
                  1695307704.369,
                  "0.5878525986591973"
               ],
               [
                  1695307709.369,
                  "0.5356932310844721"
               ],
               [
                  1695307714.369,
                  "0.5904854570081457"
               ],
               [
                  1695307719.369,
                  "0.018846995749479678"
               ],
               [
                  1695307724.369,
                  "0.5917919807901906"
               ],
               [
                  1695307729.366,
                  "0.43270877208887437"
               ],
               [
                  1695307734.366,
                  "0.2425722304016601"
               ],
               [
                  1695307739.366,
                  "0.5299813397030974"
               ],
               [
                  1695307744.366,
                  "0.4237554364274676"
               ],
               [
                  1695307749.368,
                  "0.03006518126619251"
               ],
               [
                  1695307754.366,
                  "0.19493731735982833"
               ],
               [
                  1695307759.366,
                  "0.16734790665789434"
               ],
               [
                  1695307764.366,
                  "0.02422452351192339"
               ],
               [
                  1695307769.366,
                  "0.3166106384133003"
               ],
               [
                  1695307774.366,
                  "0.007155496207695067"
               ],
               [
                  1695307779.366,
                  "0.14490544560869856"
               ],
               [
                  1695307784.366,
                  "0.2982611842254217"
               ],
               [
                  1695307789.366,
                  "0.13478355561973943"
               ],
               [
                  1695307794.366,
                  "0.0350978870815456"
               ],
               [
                  1695307799.366,
                  "0.2774545718841419"
               ],
               [
                  1695307804.366,
                  "0.410854030741694"
               ],
               [
                  1695307809.366,
                  "0.15789209874021992"
               ],
               [
                  1695307814.366,
                  "0.3386026447875662"
               ],
               [
                  1695307819.366,
                  "0.07787658610131898"
               ],
               [
                  1695307824.366,
                  "0.4806471640724862"
               ],
               [
                  1695307829.366,
                  "0.3636881516565207"
               ],
               [
                  1695307834.366,
                  "0.2826051283514942"
               ],
               [
                  1695307839.366,
                  "0.3766612498480676"
               ],
               [
                  1695307844.366,
                  "0.4633202422026087"
               ],
               [
                  1695307849.366,
                  "0.08108339246995377"
               ],
               [
                  1695307854.366,
                  "0.3667952712053595"
               ],
               [
                  1695307859.366,
                  "0.03693222542106944"
               ],
               [
                  1695307864.366,
                  "0.5391528278049328"
               ],
               [
                  1695307869.366,
                  "0.12707323105266277"
               ],
               [
                  1695307874.366,
                  "0.11281247099652159"
               ],
               [
                  1695307879.366,
                  "0.3587694702037897"
               ],
               [
                  1695307884.366,
                  "0.018624385273191435"
               ],
               [
                  1695307889.366,
                  "0.11905394347023723"
               ],
               [
                  1695307894.365,
                  "0.5773574214927863"
               ],
               [
                  1695307899.366,
                  "0.1866400362819567"
               ],
               [
                  1695307904.366,
                  "0.269728912200047"
               ],
               [
                  1695307909.366,
                  "0.3589770560780121"
               ],
               [
                  1695307914.366,
                  "0.40215265920259313"
               ],
               [
                  1695307919.366,
                  "0.1087094977465255"
               ],
               [
                  1695307924.366,
                  "0.48595120760653643"
               ],
               [
                  1695307929.365,
                  "0.417394186621444"
               ],
               [
                  1695307934.366,
                  "0.535449025491357"
               ],
               [
                  1695307939.365,
                  "0.18410974072964115"
               ],
               [
                  1695307944.366,
                  "0.4877319378820666"
               ],
               [
                  1695307949.365,
                  "0.2996758541830199"
               ],
               [
                  1695307954.366,
                  "0.21430474991868365"
               ],
               [
                  1695307959.366,
                  "0.5024072055018729"
               ],
               [
                  1695307964.365,
                  "0.38887013718822205"
               ],
               [
                  1695307969.365,
                  "0.590937601769508"
               ],
               [
                  1695307974.365,
                  "0.4265424599485539"
               ],
               [
                  1695307979.365,
                  "0.2588528513544128"
               ],
               [
                  1695307984.365,
                  "0.4484409887054114"
               ],
               [
                  1695307989.366,
                  "0.5155623356527484"
               ],
               [
                  1695307994.365,
                  "0.3976561354981615"
               ],
               [
                  1695307999.365,
                  "0.16716051243768637"
               ],
               [
                  1695308004.365,
                  "0.5398559897971429"
               ],
               [
                  1695308009.365,
                  "0.5070670438690277"
               ],
               [
                  1695308014.365,
                  "0.5991923101272184"
               ],
               [
                  1695308019.366,
                  "0.024865997014528962"
               ],
               [
                  1695308024.365,
                  "0.010671924330052263"
               ],
               [
                  1695308029.365,
                  "0.19827221408249263"
               ],
               [
                  1695308034.365,
                  "0.5971176465433301"
               ],
               [
                  1695308039.366,
                  "0.5906679207737321"
               ],
               [
                  1695308044.365,
                  "0.5842560913170289"
               ],
               [
                  1695308049.366,
                  "0.45836897752590744"
               ],
               [
                  1695308054.365,
                  "0.25085865399644014"
               ],
               [
                  1695308059.366,
                  "0.10702094779580096"
               ],
               [
                  1695308064.366,
                  "0.03861844484295085"
               ],
               [
                  1695308069.366,
                  "0.4309299105406328"
               ],
               [
                  1695308074.366,
                  "0.3754500887428659"
               ],
               [
                  1695308079.365,
                  "0.5674987342609522"
               ],
               [
                  1695308084.366,
                  "0.4450864705868901"
               ],
               [
                  1695308089.366,
                  "0.4584402196704116"
               ],
               [
                  1695308094.365,
                  "0.2567700220802085"
               ],
               [
                  1695308099.365,
                  "0.4391188619009432"
               ],
               [
                  1695308104.365,
                  "0.12279478271097521"
               ],
               [
                  1695308109.366,
                  "0.2711493803970171"
               ],
               [
                  1695308114.366,
                  "0.1397848668404964"
               ],
               [
                  1695308119.365,
                  "0.4870554369448489"
               ],
               [
                  1695308124.366,
                  "0.5825112637257354"
               ],
               [
                  1695308129.365,
                  "0.5638935948724734"
               ],
               [
                  1695308134.365,
                  "0.46581049706887834"
               ],
               [
                  1695308139.364,
                  "0.3400422779489295"
               ],
               [
                  1695308144.364,
                  "0.5805739705202743"
               ],
               [
                  1695308149.365,
                  "0.27872543994808296"
               ],
               [
                  1695308154.365,
                  "0.2867401612402728"
               ],
               [
                  1695308159.365,
                  "0.4099226843136615"
               ],
               [
                  1695308164.365,
                  "0.0309783345275495"
               ],
               [
                  1695308169.365,
                  "0.29506959552115974"
               ],
               [
                  1695308174.365,
                  "0.017983413329428877"
               ],
               [
                  1695308179.366,
                  "0.48319518114022686"
               ],
               [
                  1695308184.366,
                  "0.168634963440762"
               ],
               [
                  1695308189.366,
                  "0.5143849456190658"
               ],
               [
                  1695308194.365,
                  "0.48613319229405005"
               ],
               [
                  1695308199.365,
                  "0.05167108700372813"
               ],
               [
                  1695308204.365,
                  "0.008403085344611316"
               ],
               [
                  1695308209.366,
                  "0.2243498589990478"
               ],
               [
                  1695308214.366,
                  "0.5201642087019591"
               ],
               [
                  1695308219.365,
                  "0.44011077676767685"
               ],
               [
                  1695308224.366,
                  "0.3324571959779853"
               ],
               [
                  1695308229.366,
                  "0.05493799464797766"
               ],
               [
                  1695308234.366,
                  "0.04181371952538482"
               ],
               [
                  1695308239.365,
                  "0.149446463412782"
               ],
               [
                  1695308244.365,
                  "0.35975810402079567"
               ],
               [
                  1695308249.365,
                  "0.1366386894039393"
               ],
               [
                  1695308254.365,
                  "0.011198528903550886"
               ],
               [
                  1695308259.365,
                  "0.2821522286856609"
               ],
               [
                  1695308264.365,
                  "0.4080552269272889"
               ],
               [
                  1695308269.366,
                  "0.3920357405024122"
               ],
               [
                  1695308274.365,
                  "0.3701040943767515"
               ],
               [
                  1695308279.366,
                  "0.0434917597020692"
               ],
               [
                  1695308284.365,
                  "0.3615953427528089"
               ],
               [
                  1695308289.366,
                  "0.38425346288034357"
               ],
               [
                  1695308294.366,
                  "0.156795008039594"
               ],
               [
                  1695308299.365,
                  "0.209923053054773"
               ],
               [
                  1695308304.364,
                  "0.37948109985743705"
               ],
               [
                  1695308309.364,
                  "0.5907812611865163"
               ],
               [
                  1695308314.364,
                  "0.2429194785275779"
               ],
               [
                  1695308319.365,
                  "0.3462103112256183"
               ],
               [
                  1695308324.365,
                  "0.49901070675905534"
               ],
               [
                  1695308329.364,
                  "0.49674959154337717"
               ],
               [
                  1695308334.364,
                  "0.016458651993525475"
               ],
               [
                  1695308339.364,
                  "0.5319844582671145"
               ],
               [
                  1695308344.364,
                  "0.44099852135671624"
               ],
               [
                  1695308349.364,
                  "0.4599233233867267"
               ],
               [
                  1695308354.364,
                  "0.563177660767103"
               ],
               [
                  1695308359.365,
                  "0.5242898986893374"
               ],
               [
                  1695308364.365,
                  "0.18063951020087854"
               ],
               [
                  1695308369.364,
                  "0.4929411173199102"
               ],
               [
                  1695308374.365,
                  "0.40867726683966477"
               ],
               [
                  1695308379.364,
                  "0.5282534034413221"
               ],
               [
                  1695308384.364,
                  "0.19121251620369373"
               ],
               [
                  1695308389.365,
                  "0.5133540306239263"
               ],
               [
                  1695308394.364,
                  "0.3064685097247474"
               ],
               [
                  1695308399.365,
                  "0.5796806820371335"
               ],
               [
                  1695308404.365,
                  "0.5701837273503249"
               ],
               [
                  1695308409.364,
                  "0.4099237447587455"
               ],
               [
                  1695308414.364,
                  "0.2792362515702783"
               ],
               [
                  1695308419.365,
                  "0.2905529522718069"
               ],
               [
                  1695308424.365,
                  "0.046254172666682414"
               ],
               [
                  1695308429.365,
                  "0.29039111967136966"
               ],
               [
                  1695308434.365,
                  "0.3274599431411339"
               ],
               [
                  1695308439.364,
                  "0.34932123537030424"
               ],
               [
                  1695308444.365,
                  "0.39258357906934593"
               ],
               [
                  1695308449.364,
                  "0.4965719012219133"
               ],
               [
                  1695308454.365,
                  "0.20919528314122215"
               ],
               [
                  1695308459.365,
                  "0.5378885975206505"
               ],
               [
                  1695308464.366,
                  "0.34214951400100935"
               ],
               [
                  1695308469.365,
                  "0.17346602062934102"
               ],
               [
                  1695308474.365,
                  "0.1315727424701234"
               ],
               [
                  1695308479.365,
                  "0.2594598552721068"
               ],
               [
                  1695308484.365,
                  "0.5853567917548981"
               ],
               [
                  1695308489.365,
                  "0.4236659737097509"
               ],
               [
                  1695308494.365,
                  "0.35072576547289147"
               ],
               [
                  1695308499.365,
                  "0.26491954309121013"
               ],
               [
                  1695308504.365,
                  "0.36299490900765385"
               ],
               [
                  1695308509.365,
                  "0.25251224123851823"
               ],
               [
                  1695308514.366,
                  "0.5688741061389947"
               ],
               [
                  1695308519.366,
                  "0.08848307046914594"
               ],
               [
                  1695308524.365,
                  "0.524417424668692"
               ],
               [
                  1695308529.365,
                  "0.0762511729378389"
               ],
               [
                  1695308534.365,
                  "0.01059732283171999"
               ],
               [
                  1695308539.365,
                  "0.4019011502496407"
               ],
               [
                  1695308544.366,
                  "0.40001280670107964"
               ],
               [
                  1695308549.366,
                  "0.13794070425586757"
               ],
               [
                  1695308554.365,
                  "0.47582165057140635"
               ],
               [
                  1695308559.365,
                  "0.5545924820051017"
               ],
               [
                  1695308564.365,
                  "0.19967143600970627"
               ],
               [
                  1695308569.364,
                  "0.44364821744502025"
               ],
               [
                  1695308574.365,
                  "0.04526589758623889"
               ],
               [
                  1695308579.364,
                  "0.4987124471012607"
               ],
               [
                  1695308584.365,
                  "0.34611973457980505"
               ],
               [
                  1695308589.365,
                  "0.3951355859550483"
               ],
               [
                  1695308594.365,
                  "0.25728461185785945"
               ],
               [
                  1695308599.364,
                  "0.19784397225818295"
               ],
               [
                  1695308604.365,
                  "0.3356549242847803"
               ],
               [
                  1695308609.365,
                  "0.28079174190970235"
               ],
               [
                  1695308614.365,
                  "0.4455450618981329"
               ],
               [
                  1695308619.365,
                  "0.5825966652194146"
               ],
               [
                  1695308624.365,
                  "0.07922057473747368"
               ],
               [
                  1695308629.365,
                  "0.04574896899101888"
               ],
               [
                  1695308634.364,
                  "0.011989284239111386"
               ],
               [
                  1695308639.364,
                  "0.3699587409986823"
               ],
               [
                  1695308644.364,
                  "0.09125365884482672"
               ],
               [
                  1695308649.365,
                  "0.22090593720110685"
               ],
               [
                  1695308654.364,
                  "0.11684857506015689"
               ],
               [
                  1695308659.363,
                  "0.47456690896362297"
               ],
               [
                  1695308664.364,
                  "0.48039869659942436"
               ],
               [
                  1695308669.364,
                  "0.015180852734436368"
               ],
               [
                  1695308674.364,
                  "0.5167700190490047"
               ],
               [
                  1695308679.364,
                  "0.12881527695947792"
               ],
               [
                  1695308684.365,
                  "0.2428981566432208"
               ],
               [
                  1695308689.365,
                  "0.06957418571583796"
               ],
               [
                  1695308694.364,
                  "0.5280515237798167"
               ],
               [
                  1695308699.364,
                  "0.1569828574141604"
               ],
               [
                  1695308704.364,
                  "0.435646143255779"
               ],
               [
                  1695308709.364,
                  "0.5684334783808377"
               ],
               [
                  1695308714.363,
                  "0.18797109843225268"
               ],
               [
                  1695308719.364,
                  "0.22982356247918279"
               ],
               [
                  1695308724.364,
                  "0.5942641191659342"
               ],
               [
                  1695308729.363,
                  "0.41907483628820874"
               ],
               [
                  1695308734.364,
                  "0.5838515206696192"
               ],
               [
                  1695308739.364,
                  "0.0807338357753763"
               ],
               [
                  1695308744.365,
                  "0.11605083500170599"
               ],
               [
                  1695308749.364,
                  "0.21936911358423594"
               ],
               [
                  1695308754.363,
                  "0.35180621542496193"
               ],
               [
                  1695308759.363,
                  "0.21572196557904622"
               ],
               [
                  1695308764.364,
                  "0.052560466416347484"
               ],
               [
                  1695308769.364,
                  "0.5310880799670579"
               ],
               [
                  1695308774.363,
                  "0.4213987014215319"
               ],
               [
                  1695308779.363,
                  "0.5609432988529347"
               ],
               [
                  1695308784.363,
                  "0.47696090016703174"
               ],
               [
                  1695308789.363,
                  "0.29417018839253395"
               ],
               [
                  1695308794.363,
                  "0.10691374343070126"
               ],
               [
                  1695308799.363,
                  "0.483579679470886"
               ],
               [
                  1695308804.364,
                  "0.3324824361075128"
               ],
               [
                  1695308809.363,
                  "0.46620118101682606"
               ],
               [
                  1695308814.364,
                  "0.28435461194365486"
               ],
               [
                  1695308819.363,
                  "0.5271668592307194"
               ],
               [
                  1695308824.363,
                  "0.2596175632436689"
               ],
               [
                  1695308829.364,
                  "0.29953612708148725"
               ],
               [
                  1695308834.363,
                  "0.11193474436003126"
               ],
               [
                  1695308839.362,
                  "0.5052795623071062"
               ],
               [
                  1695308844.363,
                  "0.31550438536593317"
               ],
               [
                  1695308849.363,
                  "0.4262654674015147"
               ]
            ]
         }
      ],
      "resultType" : "matrix"
   },
   "status" : "success"
}
